coast/__init__.py
coast/_utils/__init__.py
coast/_utils/crps_util.py
coast/_utils/docsy_tools.py
coast/_utils/experiments_file_handling.py
coast/_utils/general_utils.py
coast/_utils/logging_util.py
coast/_utils/mask_maker.py
coast/_utils/plot_util.py
coast/_utils/process_data.py
coast/_utils/seasons.py
coast/_utils/stats_util.py
coast/_utils/xesmf_convert.py
coast/data/__init__.py
coast/data/altimetry.py
coast/data/argos.py
coast/data/coast.py
coast/data/config_parser.py
coast/data/config_structure.py
coast/data/copernicus.py
coast/data/glider.py
coast/data/gridded.py
coast/data/index.py
coast/data/lagrangian.py
coast/data/oceanparcels.py
coast/data/opendap.py
coast/data/profile.py
coast/data/tidegauge.py
coast/data/timeseries.py
coast/data/track.py
coast/diagnostics/__init__.py
coast/diagnostics/circulation.py
coast/diagnostics/climatology.py
coast/diagnostics/contour.py
coast/diagnostics/eof.py
coast/diagnostics/gridded_stratification.py
coast/diagnostics/profile_analysis.py
coast/diagnostics/tidegauge_analysis.py
coast/diagnostics/transect.py
COAsT-3.3.0.dist-info/LICENSE
COAsT-3.3.0.dist-info/METADATA
COAsT-3.3.0.dist-info/WHEEL
COAsT-3.3.0.dist-info/top_level.txt
COAsT-3.3.0.dist-info/RECORD
